setup.py
happierfuntokenizing/__init__.py
happierfuntokenizing/happierfuntokenizing.py
happierfuntokenizing.egg-info/PKG-INFO
happierfuntokenizing.egg-info/SOURCES.txt
happierfuntokenizing.egg-info/dependency_links.txt
happierfuntokenizing.egg-info/top_level.txt