Metadata-Version: 1.1
Name: happierfuntokenizing
Version: 1.5.7
Summary: This code implements a basic, Twitter-aware tokenizer. Originally developed by Christopher Potts and 
Home-page: http://dlatk.wwbp.org
Author: Christopher Potts, H. Andrew Schwartz, Maarten Sap, Salvatore Giorgi
Author-email: hansens@sas.upenn.edu, sgiorgi@sas.upenn.edu
License: GNU General Public License v3 (GPLv3)
Download-URL: https://github.com/dlatk/happierfuntokenizing
Platform: UNKNOWN
Classifier: Environment :: Console
Classifier: Natural Language :: English
Classifier: Intended Audience :: End Users/Desktop
Classifier: Intended Audience :: Developers
Classifier: Intended Audience :: Science/Research
Classifier: Programming Language :: Python
Classifier: Programming Language :: Python :: 2
Classifier: Programming Language :: Python :: 2.7
Classifier: Topic :: Scientific/Engineering
